spyonweb/__init__.py
spyonweb/api.py
spyonweb/cli.py
spyonweb-0.1.dist-info/LICENSE
spyonweb-0.1.dist-info/METADATA
spyonweb-0.1.dist-info/WHEEL
spyonweb-0.1.dist-info/entry_points.txt
spyonweb-0.1.dist-info/top_level.txt
spyonweb-0.1.dist-info/RECORD
