Metadata-Version: 2.1
Name: spyonweb
Version: 0.1
Summary: SpyOnWeb python wrapper
Home-page: https://github.com/Te-k/spyonweb
Author: Tek
Author-email: tek@randhome.io
License: MIT
Keywords: osint
Platform: UNKNOWN
Classifier: Programming Language :: Python :: 3
Classifier: License :: OSI Approved :: MIT License
Classifier: Operating System :: OS Independent
Requires-Dist: requests
Requires-Dist: configparser
